nidmresults/__init__.py
nidmresults/exporter.py
nidmresults/graph.py
nidmresults/load.py
nidmresults/prefixes.csv
nidmresults/objects/__init__.py
nidmresults/objects/constants.py
nidmresults/objects/constants_rdflib.py
nidmresults/objects/contrast.py
nidmresults/objects/generic.py
nidmresults/objects/inference.py
nidmresults/objects/modelfitting.py
nidmresults/owl/__init__.py
nidmresults/owl/nidm-results_020.owl
nidmresults/owl/nidm-results_100.owl
nidmresults/owl/nidm-results_110.owl
nidmresults/owl/nidm-results_120.owl
nidmresults/owl/nidm-results_130.owl
nidmresults/owl/owl_reader.py
nidmresults/test/__init__.py
nidmresults/test/check_consistency.py
nidmresults/test/test_commons.py
nidmresults/test/test_results_doc.py
nidmresults-2.1.0.data/scripts/nidm_mkda_convert
nidmresults-2.1.0.data/scripts/nidmreader
nidmresults-2.1.0.data/scripts/nidmresults
nidmresults-2.1.0.dist-info/METADATA
nidmresults-2.1.0.dist-info/RECORD
nidmresults-2.1.0.dist-info/WHEEL
nidmresults-2.1.0.dist-info/top_level.txt
test/__init__.py
test/test_reader.py
