Metadata-Version: 2.1
Name: nidmresults
Version: 2.1.0
Summary: Export of neuroimaging statistical results using NIDM as specified at http://nidm.nidash.org/specs/nidm-results.html.
Home-page: https://github.com/incf-nidash/nidmresults
Author: Camille Maumet
Author-email: c.m.j.maumet@warwick.ac.uk
License: MIT
Keywords: Prov,NIDM,Provenance
Platform: UNKNOWN
Classifier: Development Status :: 3 - Alpha
Classifier: Topic :: Utilities
Classifier: License :: OSI Approved :: MIT License
Requires-Dist: rdflib (>=4.2.0)
Requires-Dist: rdflib-jsonld
Requires-Dist: prov (>=1.5.0)
Requires-Dist: nibabel
Requires-Dist: numpy
Requires-Dist: future
Requires-Dist: requests
Requires-Dist: pyld
